pymchat/__init__.py
pymchat/chat.py
pymchat/exceptions.py
pymchat/message.py
pymchat-1.0.dist-info/LICENSE
pymchat-1.0.dist-info/METADATA
pymchat-1.0.dist-info/WHEEL
pymchat-1.0.dist-info/top_level.txt
pymchat-1.0.dist-info/RECORD
