Metadata-Version: 2.1
Name: pymchat
Version: 1.0
Summary: A Simple and easy-to-use Python Library to read and interact with Minecraft's Chat in real time.
Home-page: https://github.com/MrKelpy/PyMChat
Author: Alexandre Silva // MrKelpy
Author-email: alexandresilva.coding@gmail.com
License: UNKNOWN
Platform: UNKNOWN
Classifier: Programming Language :: Python :: 3
Classifier: License :: OSI Approved :: GNU General Public License v3 (GPLv3)
Classifier: Operating System :: OS Independent
Requires-Python: >=3.6
License-File: LICENSE
Requires-Dist: keyboard
Requires-Dist: pygetwindow
